{"createdAt":1613724832795,"data":{"table":[{"title":"Secret Night","author":"monochrome","link":"https://nhentai.net/g/348121/","tier":"B+","time":"1613689157064","date":"2 minutes"},{"title":"My beloved Mister & My beloved Runaway Girl - Chapter 2","author":"Miyabi","link":"https://nhentai.net/g/170203/","tier":"D+","time":"1613601742071","date":"1 days"},{"title":"My beloved Mister & My beloved Runaway Girl - Chapter 1","author":"Miyabi","link":"https://nhentai.net/g/169754/","tier":"C","time":"1613601735292","date":"1 days"},{"title":"The Dreamest Girl","author":"Tamabi","link":"https://nhentai.net/g/348148","tier":"A-","time":"1613586029069","date":"1 days"},{"title":"Share Loveru Kouhen","author":"Miyabe Kiwi","link":"https://nhentai.net/g/347855/","tier":"A+","time":"1613544492886","date":"1 days"},{"title":"Share Loveru","author":"Miyabe Kiwi","link":"https://nhentai.net/g/347521/","tier":"A","time":"1613544474073","date":"1 days"},{"title":"Hanayome wa Shinkai Taihou-chan","author":"Kamizuki Shiki","link":"https://nhentai.net/g/153734/","tier":"B","time":"1613521246985","date":"1 days"},{"title":"Kitsume na Kimono Niizuma to Kyoukotoba Ecchi","author":"Mutou Koucha","link":"https://nhentai.net/g/347788/","tier":"A+","time":"1613521053098","date":"1 days"},{"title":"A Week-Long Relation Between a Gyaru and an Introvert.","author":"Tamabi","link":"https://nhentai.net/g/347653/","tier":"S-","time":"1613255946623","date":"5 days"},{"title":"Temptation Swimsuit","author":"Toguchi Masaya","link":"https://nhentai.net/g/89719","tier":"D","time":"1613171789882","date":"5 days"}]}}